.gitignore
MANIFEST.in
README.rst
bootstrap.py
buildout.cfg
setup.py
collective/__init__.py
collective.js.timeago.egg-info/PKG-INFO
collective.js.timeago.egg-info/SOURCES.txt
collective.js.timeago.egg-info/dependency_links.txt
collective.js.timeago.egg-info/entry_points.txt
collective.js.timeago.egg-info/namespace_packages.txt
collective.js.timeago.egg-info/not-zip-safe
collective.js.timeago.egg-info/requires.txt
collective.js.timeago.egg-info/top_level.txt
collective/js/__init__.py
collective/js/timeago/__init__.py
collective/js/timeago/configure.zcml
collective/js/timeago/interfaces.py
collective/js/timeago/upgrades.py
collective/js/timeago/upgrades.zcml
collective/js/timeago/viewlet.py
collective/js/timeago/viewlet_timeago.pt
collective/js/timeago/example/__init__.py
collective/js/timeago/example/configure.zcml
collective/js/timeago/example/example.pt
collective/js/timeago/profiles/default/browserlayer.xml
collective/js/timeago/profiles/default/jsregistry.xml
collective/js/timeago/profiles/default/metadata.xml
collective/js/timeago/resources/jquery.timeago.js
collective/js/timeago/resources/locales/README.md
collective/js/timeago/resources/locales/jquery.timeago.ar.js
collective/js/timeago/resources/locales/jquery.timeago.bg.js
collective/js/timeago/resources/locales/jquery.timeago.bs.js
collective/js/timeago/resources/locales/jquery.timeago.ca.js
collective/js/timeago/resources/locales/jquery.timeago.cy.js
collective/js/timeago/resources/locales/jquery.timeago.cz.js
collective/js/timeago/resources/locales/jquery.timeago.da.js
collective/js/timeago/resources/locales/jquery.timeago.de.js
collective/js/timeago/resources/locales/jquery.timeago.el.js
collective/js/timeago/resources/locales/jquery.timeago.en-short.js
collective/js/timeago/resources/locales/jquery.timeago.en.js
collective/js/timeago/resources/locales/jquery.timeago.es.js
collective/js/timeago/resources/locales/jquery.timeago.fa.js
collective/js/timeago/resources/locales/jquery.timeago.fi.js
collective/js/timeago/resources/locales/jquery.timeago.fr.js
collective/js/timeago/resources/locales/jquery.timeago.he.js
collective/js/timeago/resources/locales/jquery.timeago.hr.js
collective/js/timeago/resources/locales/jquery.timeago.hu.js
collective/js/timeago/resources/locales/jquery.timeago.hy.js
collective/js/timeago/resources/locales/jquery.timeago.id.js
