Metadata-Version: 1.0
Name: collective.js.timeago
Version: 1.1
Summary: Register JQuery timeago plugin into Plone resource registry
Home-page: https://github.com/collective/collective.js.timeago
Author: JeanMichel FRANOIS
Author-email: toutpt@gmail.com
License: GPL
Keywords: plone javascript
Platform: UNKNOWN
Classifier: Environment :: Web Environment
Classifier: License :: OSI Approved :: GNU General Public License (GPL)
Classifier: Operating System :: OS Independent
Classifier: Framework :: Plone
Classifier: Framework :: Plone :: 4.0
Classifier: Framework :: Plone :: 4.1
Classifier: Framework :: Plone :: 4.2
Classifier: Programming Language :: Python
